sici/__init__.py
sici/ast_generator.py
sici/cache.py
sici/canonical.py
sici/compiler.py
sici/dag.py
sici/export.py
sici/identity_checker.py
sici/metrics.py
sici/models.py
sici/precompiled.py
sici/rewrite.py
sici/trace.py
sici/tree.py
sici/utils.py
sici/visual.py
sici/examples/sici_cache/ablation_synthetic_symbolic.py
sici/examples/sici_cache/benchmark_suite.py
sici/examples/sici_cache/cse_comparison.py
sici/examples/sici_cache/failure_existing.py
sici/examples/sici_cache/large_scale.py
sici/examples/sici_cache/mc_convergence.py
sici/examples/sici_cache/numeric_cache_mode.py
sici/examples/sici_cache/numeric_cache_synthetic.py
sici/examples/sici_cache/real_data_cross_query.py
sici/examples/sici_cache/whittemore_causaleffect_compare.py
sici/examples/sici_trace/alarm_numeric.py
sici/examples/sici_trace/asia_numeric.py
sici/examples/sici_trace/backdoor.py
sici/examples/sici_trace/benchmark_large_dag.py
sici/examples/sici_trace/frontdoor.py
sici/examples/sici_trace/hepar2_experiment.py
sici/examples/sici_trace/large_scale_identifibility_benckmark.py
sici/examples/sici_trace/mixed_discrete_continuous_numeric.py
sici/examples/sici_trace/multiple_queries.py
sici/examples/sici_trace/two_confounders_numeric.py
sici-0.1.3.dist-info/licenses/LICENSE.md
sici-0.1.3.dist-info/METADATA
sici-0.1.3.dist-info/WHEEL
sici-0.1.3.dist-info/top_level.txt
sici-0.1.3.dist-info/RECORD
