Metadata-Version: 2.4
Name: sici
Version: 0.1.3
Summary: Symbolic Integration for Causal Inference
Author-email: Ruyu Bai <bairuyu1218@gmail.com>
Requires-Python: >=3.9
License-File: LICENSE.md
Requires-Dist: sympy
Requires-Dist: scipy
Requires-Dist: graphviz
Requires-Dist: numpy
Requires-Dist: pandas
Requires-Dist: pytest
Requires-Dist: pgmpy
Provides-Extra: full
Requires-Dist: ananke; extra == "full"
Dynamic: license-file
